pinterest_dl/__init__.py
pinterest_dl/cli.py
pinterest_dl/exceptions.py
pinterest_dl/api/__init__.py
pinterest_dl/api/api.py
pinterest_dl/api/bookmark_manager.py
pinterest_dl/api/endpoints.py
pinterest_dl/api/pinterest_response.py
pinterest_dl/common/dump.py
pinterest_dl/common/ensure_executable.py
pinterest_dl/common/io.py
pinterest_dl/common/logging.py
pinterest_dl/common/progress_bar.py
pinterest_dl/data_model/__init__.py
pinterest_dl/domain/__init__.py
pinterest_dl/domain/browser.py
pinterest_dl/domain/cookies.py
pinterest_dl/domain/media.py
pinterest_dl/download/__init__.py
pinterest_dl/download/downloader.py
pinterest_dl/download/http_client.py
pinterest_dl/download/request_builder.py
pinterest_dl/download/video/__init__.py
pinterest_dl/download/video/hls_processor.py
pinterest_dl/download/video/key_cache.py
pinterest_dl/download/video/segment_info.py
pinterest_dl/low_level/__init__.py
pinterest_dl/parsers/response.py
pinterest_dl/scrapers/__init__.py
pinterest_dl/scrapers/api_scraper.py
pinterest_dl/scrapers/operations.py
pinterest_dl/scrapers/playwright_scraper.py
pinterest_dl/scrapers/webdriver_scraper.py
pinterest_dl/storage/media.py
pinterest_dl/webdriver/__init__.py
pinterest_dl/webdriver/browser.py
pinterest_dl/webdriver/driver.py
pinterest_dl/webdriver/driver_installer.py
pinterest_dl/webdriver/playwright_browser.py
pinterest_dl/webdriver/playwright_driver.py
pinterest_dl-1.0.0.dist-info/licenses/LICENSE
pinterest_dl-1.0.0.dist-info/METADATA
pinterest_dl-1.0.0.dist-info/WHEEL
pinterest_dl-1.0.0.dist-info/entry_points.txt
pinterest_dl-1.0.0.dist-info/top_level.txt
pinterest_dl-1.0.0.dist-info/RECORD
