Metadata-Version: 2.4
Name: pinterest-dl
Version: 1.0.0
Summary: An unofficial Pinterest image downloader
Author-email: sean1832 <dev@zekezhang.com>
License: Apache-2.0
Project-URL: Homepage, https://github.com/sean1832/pinterest-dl
Project-URL: Issues, https://github.com/sean1832/pinterest-dl/issues
Keywords: pinterest,image downloader,web scraping
Classifier: Development Status :: 4 - Beta
Classifier: Intended Audience :: Developers
Classifier: License :: OSI Approved :: Apache Software License
Classifier: Programming Language :: Python
Classifier: Environment :: Console
Requires-Python: >=3.10
License-File: LICENSE
Requires-Dist: playwright>=1.40.0
Requires-Dist: selenium>=4.26.1
Requires-Dist: pillow==10.4.0
Requires-Dist: tqdm
Requires-Dist: pyexiv2
Requires-Dist: requests
Requires-Dist: deprecated
Requires-Dist: m3u8
Requires-Dist: cryptography
Provides-Extra: dev
Requires-Dist: pytest>=7.0.0; extra == "dev"
Requires-Dist: pytest-mock>=3.10.0; extra == "dev"
Dynamic: license-file
